README
setup.py
ircutils3/__init__.py
ircutils3/bot.py
ircutils3/client.py
ircutils3/connection.py
ircutils3/ctcp.py
ircutils3/events.py
ircutils3/format.py
ircutils3/ident.py
ircutils3/protocol.py
ircutils3/responses.py
ircutils3.egg-info/PKG-INFO
ircutils3.egg-info/SOURCES.txt
ircutils3.egg-info/dependency_links.txt
ircutils3.egg-info/top_level.txt